{
  "name": "enquiryTenant",
  "plural": "enquiryTenant",
  "base": "PersistedModel",
  "idInjection": true,
  "options": {
    "validateUpsert": true,
    "mysql": {
      "table": "kb_enquiry_tenant"
    }
  },
  "properties": {
    "esId": {
      "type": "String",
      "id": 1,
      "required": true,
      "length": 100,
      "precision": null,
      "scale": null,
      "mysql": {
        "columnName": "es_id",
        "dataType": "varchar",
        "dataLength": 100,
        "dataPrecision": null,
        "dataScale": null,
        "nullable": "N"
      }
    },
    "tenantId": {
      "type": "String",
      "required": false,
      "length": 100,
      "precision": null,
      "scale": null,
      "mysql": {
        "columnName": "tenant_id",
        "dataType": "varchar",
        "dataLength": 100,
        "dataPrecision": null,
        "dataScale": null,
        "nullable": "Y"
      }
    },
    "enquiryId": {
      "type": "String",
      "required": false,
      "length": 100,
      "precision": null,
      "scale": null,
      "mysql": {
        "columnName": "enquiry_id",
        "dataType": "varchar",
        "dataLength": 100,
        "dataPrecision": null,
        "dataScale": null,
        "nullable": "Y"
      }
    },
    "createdTs": {
      "type": "Date",
      "required": false,
      "length": null,
      "precision": null,
      "scale": null,
      "mysql": {
        "columnName": "created_ts",
        "dataType": "datetime",
        "dataLength": null,
        "dataPrecision": null,
        "dataScale": null,
        "nullable": "Y"
      }
    },
    "updatedTs": {
      "type": "Date",
      "required": false,
      "length": null,
      "precision": null,
      "scale": null,
      "mysql": {
        "columnName": "updated_ts",
        "dataType": "datetime",
        "dataLength": null,
        "dataPrecision": null,
        "dataScale": null,
        "nullable": "Y"
      }
    },
    "isDeleted": {
      "type": "Number",
      "required": false,
      "length": null,
      "precision": 3,
      "scale": 0,
      "mysql": {
        "columnName": "is_deleted",
        "dataType": "tinyint",
        "dataLength": null,
        "dataPrecision": 3,
        "dataScale": 0,
        "nullable": "Y"
      }
    }
  },
  "validations": [],
  "relations": {},
  "acls": [],
  "methods": {}
}
